odoo/addons/ssi_accountant_general_audit_ws_ra130/README.rst
odoo/addons/ssi_accountant_general_audit_ws_ra130/__init__.py
odoo/addons/ssi_accountant_general_audit_ws_ra130/__manifest__.py
odoo/addons/ssi_accountant_general_audit_ws_ra130/data/accountant_general_audit_worksheet_type_data.xml
odoo/addons/ssi_accountant_general_audit_ws_ra130/data/approval_template_data.xml
odoo/addons/ssi_accountant_general_audit_ws_ra130/data/ir_sequence_data.xml
odoo/addons/ssi_accountant_general_audit_ws_ra130/data/policy_template_data.xml
odoo/addons/ssi_accountant_general_audit_ws_ra130/data/sequence_template_data.xml
odoo/addons/ssi_accountant_general_audit_ws_ra130/models/__init__.py
odoo/addons/ssi_accountant_general_audit_ws_ra130/models/accountant_general_audit_ws_ra130.py
odoo/addons/ssi_accountant_general_audit_ws_ra130/models/accountant_general_audit_ws_ra1301.py
odoo/addons/ssi_accountant_general_audit_ws_ra130/models/accountant_general_audit_ws_ra1301_materiality_mapping.py
odoo/addons/ssi_accountant_general_audit_ws_ra130/security/ir.model.access.csv
odoo/addons/ssi_accountant_general_audit_ws_ra130/security/ir_module_category_data.xml
odoo/addons/ssi_accountant_general_audit_ws_ra130/security/ir_rule_data.xml
odoo/addons/ssi_accountant_general_audit_ws_ra130/security/res_group_data.xml
odoo/addons/ssi_accountant_general_audit_ws_ra130/static/description/icon.png
odoo/addons/ssi_accountant_general_audit_ws_ra130/views/accountant_general_audit_ws_ra1301_views.xml
odoo/addons/ssi_accountant_general_audit_ws_ra130/views/accountant_general_audit_ws_ra130_views.xml
odoo14_addon_ssi_accountant_general_audit_ws_ra130-14.0.1.5.2.dev1.dist-info/METADATA
odoo14_addon_ssi_accountant_general_audit_ws_ra130-14.0.1.5.2.dev1.dist-info/WHEEL
odoo14_addon_ssi_accountant_general_audit_ws_ra130-14.0.1.5.2.dev1.dist-info/top_level.txt
odoo14_addon_ssi_accountant_general_audit_ws_ra130-14.0.1.5.2.dev1.dist-info/RECORD
